{
  "instance": "Instance3",
  "source_kind": "table3",
  "source_file": "E:/研究生代码/复现parallel-truck-drone-small-instances/outputs/routes_bundle_10instances/Instance3_table3_fixedx_combo_15_18.json",
  "scenario_index": 0,
  "open_depots_internal": [
    15,
    18
  ],
  "explicit_solution": {
    "tt": {
      "15": [
        15,
        5,
        9,
        11,
        2,
        14,
        14,
        2,
        11,
        7
      ],
      "18": [
        18,
        8,
        0,
        10,
        3,
        10,
        0,
        8
      ]
    },
    "ds": {
      "15": [
        4,
        1,
        13
      ],
      "18": [
        12,
        6
      ]
    }
  },
  "arrival_sim": {
    "objective": 11.033333333333333
  },
  "arrival_sim_on_model_normalized_walk": {
    "objective": 11.033333333333333,
    "tt": {
      "15": [
        15,
        5,
        9,
        11,
        2,
        14,
        2,
        11,
        7,
        11,
        9,
        15
      ],
      "18": [
        18,
        8,
        0,
        10,
        3,
        10,
        0,
        8,
        18
      ]
    },
    "ds": {
      "15": [
        4,
        1,
        13
      ],
      "18": [
        12,
        6
      ]
    }
  },
  "derived_from_explicit_solution": {
    "depots": [
      {
        "depot_internal": 15,
        "raw_tour": [
          15,
          5,
          9,
          11,
          2,
          14,
          14,
          2,
          11,
          7
        ],
        "closed_tour_used_for_y": [
          15,
          5,
          9,
          11,
          2,
          14,
          14,
          2,
          11,
          7,
          11,
          9,
          15
        ],
        "normalized_start_inserted": false,
        "auto_closed_back_to_depot": true,
        "raw_arc_count": 11,
        "unique_arc_count": 11,
        "repeated_directed_arcs": [],
        "first_visit_demands_in_tour": [
          5,
          9,
          11,
          2,
          14,
          7
        ],
        "drone_sequence": [
          4,
          1,
          13
        ]
      },
      {
        "depot_internal": 18,
        "raw_tour": [
          18,
          8,
          0,
          10,
          3,
          10,
          0,
          8
        ],
        "closed_tour_used_for_y": [
          18,
          8,
          0,
          10,
          3,
          10,
          0,
          8,
          18
        ],
        "normalized_start_inserted": false,
        "auto_closed_back_to_depot": true,
        "raw_arc_count": 8,
        "unique_arc_count": 8,
        "repeated_directed_arcs": [],
        "first_visit_demands_in_tour": [
          8,
          0,
          10,
          3
        ],
        "drone_sequence": [
          12,
          6
        ]
      }
    ],
    "y_on_by_depot": {
      "15": [
        [
          2,
          11
        ],
        [
          2,
          14
        ],
        [
          5,
          9
        ],
        [
          7,
          11
        ],
        [
          9,
          11
        ],
        [
          9,
          15
        ],
        [
          11,
          2
        ],
        [
          11,
          7
        ],
        [
          11,
          9
        ],
        [
          14,
          2
        ],
        [
          15,
          5
        ]
      ],
      "18": [
        [
          0,
          8
        ],
        [
          0,
          10
        ],
        [
          3,
          10
        ],
        [
          8,
          0
        ],
        [
          8,
          18
        ],
        [
          10,
          0
        ],
        [
          10,
          3
        ],
        [
          18,
          8
        ]
      ]
    },
    "c_on_by_depot": {
      "15": [
        2,
        5,
        7,
        9,
        11,
        14
      ],
      "18": [
        0,
        3,
        8,
        10
      ]
    },
    "z_on_by_depot": {
      "15": [
        1,
        4,
        13
      ],
      "18": [
        6,
        12
      ]
    },
    "w_on_by_depot": {
      "15": [],
      "18": []
    },
    "a_on_by_depot": {
      "15": [],
      "18": []
    },
    "b_on_links": []
  },
  "strict_order_fixed_binaries_derived_from_explicit_solution": {
    "depots": [
      {
        "depot_internal": 15,
        "raw_tour": [
          15,
          5,
          9,
          11,
          2,
          14,
          14,
          2,
          11,
          7
        ],
        "normalized_tour": [
          15,
          5,
          9,
          11,
          2,
          14,
          2,
          11,
          7
        ],
        "closed_tour_used_for_model": [
          15,
          5,
          9,
          11,
          2,
          14,
          2,
          11,
          7,
          11,
          9,
          15
        ],
        "removed_consecutive_duplicates": 1,
        "auto_closed_back_to_depot": true,
        "kept_arcs": [
          [
            15,
            5
          ],
          [
            5,
            9
          ],
          [
            9,
            11
          ],
          [
            11,
            2
          ],
          [
            2,
            14
          ],
          [
            14,
            2
          ],
          [
            2,
            11
          ],
          [
            11,
            7
          ],
          [
            7,
            11
          ],
          [
            11,
            9
          ],
          [
            9,
            15
          ]
        ],
        "invalid_or_skipped_arcs": [],
        "truck_demands_fixed_in_c": [
          5,
          9,
          11,
          2,
          14,
          7
        ],
        "drone_demands_fixed_in_z": [
          4,
          1,
          13
        ]
      },
      {
        "depot_internal": 18,
        "raw_tour": [
          18,
          8,
          0,
          10,
          3,
          10,
          0,
          8
        ],
        "normalized_tour": [
          18,
          8,
          0,
          10,
          3,
          10,
          0,
          8
        ],
        "closed_tour_used_for_model": [
          18,
          8,
          0,
          10,
          3,
          10,
          0,
          8,
          18
        ],
        "removed_consecutive_duplicates": 0,
        "auto_closed_back_to_depot": true,
        "kept_arcs": [
          [
            18,
            8
          ],
          [
            8,
            0
          ],
          [
            0,
            10
          ],
          [
            10,
            3
          ],
          [
            3,
            10
          ],
          [
            10,
            0
          ],
          [
            0,
            8
          ],
          [
            8,
            18
          ]
        ],
        "invalid_or_skipped_arcs": [],
        "truck_demands_fixed_in_c": [
          8,
          0,
          10,
          3
        ],
        "drone_demands_fixed_in_z": [
          12,
          6
        ]
      }
    ],
    "warnings": [],
    "y_on_by_depot": {
      "15": [
        [
          2,
          11
        ],
        [
          2,
          14
        ],
        [
          5,
          9
        ],
        [
          7,
          11
        ],
        [
          9,
          11
        ],
        [
          9,
          15
        ],
        [
          11,
          2
        ],
        [
          11,
          7
        ],
        [
          11,
          9
        ],
        [
          14,
          2
        ],
        [
          15,
          5
        ]
      ],
      "18": [
        [
          0,
          8
        ],
        [
          0,
          10
        ],
        [
          3,
          10
        ],
        [
          8,
          0
        ],
        [
          8,
          18
        ],
        [
          10,
          0
        ],
        [
          10,
          3
        ],
        [
          18,
          8
        ]
      ]
    },
    "c_on_by_depot": {
      "15": [
        2,
        5,
        7,
        9,
        11,
        14
      ],
      "18": [
        0,
        3,
        8,
        10
      ]
    },
    "z_on_by_depot": {
      "15": [
        1,
        4,
        13
      ],
      "18": [
        6,
        12
      ]
    },
    "w_on_by_depot": {
      "15": [
        [
          2,
          14
        ],
        [
          5,
          9
        ],
        [
          7,
          11
        ],
        [
          9,
          11
        ],
        [
          11,
          2
        ],
        [
          14,
          2
        ]
      ],
      "18": [
        [
          0,
          10
        ],
        [
          3,
          10
        ],
        [
          8,
          0
        ],
        [
          10,
          3
        ]
      ]
    },
    "a_on_by_depot": {
      "15": [
        [
          2,
          11
        ],
        [
          5,
          9
        ],
        [
          7,
          11
        ],
        [
          9,
          15
        ],
        [
          11,
          9
        ],
        [
          14,
          2
        ]
      ],
      "18": [
        [
          0,
          8
        ],
        [
          3,
          10
        ],
        [
          8,
          18
        ],
        [
          10,
          0
        ]
      ]
    },
    "b_on_links": [
      [
        0,
        8,
        18
      ],
      [
        2,
        11,
        7
      ],
      [
        3,
        10,
        0
      ],
      [
        7,
        11,
        9
      ],
      [
        10,
        0,
        8
      ],
      [
        11,
        9,
        15
      ],
      [
        14,
        2,
        11
      ]
    ]
  },
  "paper_exact_fixed_primary_binaries_only": {
    "status": 2,
    "status_name": "OPTIMAL",
    "objective": 11.033333333333333,
    "best_bound": 11.033333333333333,
    "runtime_sec": 0.0019998550415039062,
    "objective_components_incumbent": {
      "truck_flow_component": 143.0,
      "truck_arc_component": 57.0,
      "drone_component": 79.5,
      "flow_minus_arc_plus_drone": 165.5,
      "normalization_coeff": 0.06666666666666667,
      "normalized_objective_from_components": 11.033333333333333
    },
    "solution_details": {
      "scenario_routes": [
        {
          "scenario_index": 0,
          "depots": [
            {
              "depot_internal": 15,
              "truck_assigned_demands": [
                2,
                5,
                7,
                9,
                11,
                14
              ],
              "drone_assigned_demands": [
                1,
                4,
                13
              ],
              "truck_active_arcs": [
                [
                  2,
                  11
                ],
                [
                  2,
                  14
                ],
                [
                  5,
                  9
                ],
                [
                  7,
                  11
                ],
                [
                  9,
                  11
                ],
                [
                  9,
                  15
                ],
                [
                  11,
                  2
                ],
                [
                  11,
                  7
                ],
                [
                  11,
                  9
                ],
                [
                  14,
                  2
                ],
                [
                  15,
                  5
                ]
              ],
              "truck_walk": [
                15,
                5,
                9,
                11,
                2,
                14,
                2,
                11,
                7,
                11,
                9,
                15
              ],
              "truck_walk_euler": [
                15,
                5,
                9,
                11,
                2,
                14,
                2,
                11,
                7,
                11,
                9,
                15
              ],
              "truck_unused_arcs_after_walk": [],
              "truck_walk_model_order": [
                15,
                5,
                9,
                11,
                2,
                14,
                2,
                11,
                7,
                11,
                9,
                15
              ],
              "truck_unused_arcs_after_model_order": [],
              "truck_walk_eval_preferred": [
                15,
                5,
                9,
                11,
                2,
                14,
                2,
                11,
                7,
                11,
                9,
                15
              ],
              "truck_first_departure_arcs_w": [
                [
                  2,
                  14
                ],
                [
                  5,
                  9
                ],
                [
                  7,
                  11
                ],
                [
                  9,
                  11
                ],
                [
                  11,
                  2
                ],
                [
                  14,
                  2
                ]
              ],
              "truck_last_departure_arcs_a": [
                [
                  2,
                  11
                ],
                [
                  5,
                  9
                ],
                [
                  7,
                  11
                ],
                [
                  9,
                  15
                ],
                [
                  11,
                  9
                ],
                [
                  14,
                  2
                ]
              ],
              "truck_successor_links_b": [
                [
                  14,
                  2,
                  11
                ],
                [
                  11,
                  9,
                  15
                ],
                [
                  2,
                  11,
                  7
                ],
                [
                  7,
                  11,
                  9
                ]
              ],
              "drone_sequence_spt": [
                4,
                1,
                13
              ],
              "drone_arrival_time": {
                "4": 4.0,
                "1": 14.5,
                "13": 31.0
              }
            },
            {
              "depot_internal": 18,
              "truck_assigned_demands": [
                0,
                3,
                8,
                10
              ],
              "drone_assigned_demands": [
                6,
                12
              ],
              "truck_active_arcs": [
                [
                  0,
                  8
                ],
                [
                  0,
                  10
                ],
                [
                  3,
                  10
                ],
                [
                  8,
                  0
                ],
                [
                  8,
                  18
                ],
                [
                  10,
                  0
                ],
                [
                  10,
                  3
                ],
                [
                  18,
                  8
                ]
              ],
              "truck_walk": [
                18,
                8,
                0,
                10,
                3,
                10,
                0,
                8,
                18
              ],
              "truck_walk_euler": [
                18,
                8,
                0,
                10,
                3,
                10,
                0,
                8,
                18
              ],
              "truck_unused_arcs_after_walk": [],
              "truck_walk_model_order": [
                18,
                8,
                0,
                10,
                3,
                10,
                0,
                8,
                18
              ],
              "truck_unused_arcs_after_model_order": [],
              "truck_walk_eval_preferred": [
                18,
                8,
                0,
                10,
                3,
                10,
                0,
                8,
                18
              ],
              "truck_first_departure_arcs_w": [
                [
                  0,
                  10
                ],
                [
                  3,
                  10
                ],
                [
                  8,
                  0
                ],
                [
                  10,
                  3
                ]
              ],
              "truck_last_departure_arcs_a": [
                [
                  0,
                  8
                ],
                [
                  3,
                  10
                ],
                [
                  8,
                  18
                ],
                [
                  10,
                  0
                ]
              ],
              "truck_successor_links_b": [
                [
                  10,
                  0,
                  8
                ],
                [
                  0,
                  8,
                  18
                ],
                [
                  3,
                  10,
                  0
                ]
              ],
              "drone_sequence_spt": [
                12,
                6
              ],
              "drone_arrival_time": {
                "12": 5.5,
                "6": 24.5
              }
            }
          ]
        }
      ]
    }
  },
  "paper_exact_fixed_primary_and_order_binaries": {
    "status": 2,
    "status_name": "OPTIMAL",
    "objective": 11.033333333333333,
    "best_bound": 11.033333333333333,
    "runtime_sec": 0.0,
    "objective_components_incumbent": {
      "truck_flow_component": 143.0,
      "truck_arc_component": 57.0,
      "drone_component": 79.5,
      "flow_minus_arc_plus_drone": 165.5,
      "normalization_coeff": 0.06666666666666667,
      "normalized_objective_from_components": 11.033333333333333
    },
    "solution_details": {
      "scenario_routes": [
        {
          "scenario_index": 0,
          "depots": [
            {
              "depot_internal": 15,
              "truck_assigned_demands": [
                2,
                5,
                7,
                9,
                11,
                14
              ],
              "drone_assigned_demands": [
                1,
                4,
                13
              ],
              "truck_active_arcs": [
                [
                  2,
                  11
                ],
                [
                  2,
                  14
                ],
                [
                  5,
                  9
                ],
                [
                  7,
                  11
                ],
                [
                  9,
                  11
                ],
                [
                  9,
                  15
                ],
                [
                  11,
                  2
                ],
                [
                  11,
                  7
                ],
                [
                  11,
                  9
                ],
                [
                  14,
                  2
                ],
                [
                  15,
                  5
                ]
              ],
              "truck_walk": [
                15,
                5,
                9,
                11,
                2,
                14,
                2,
                11,
                7,
                11,
                9,
                15
              ],
              "truck_walk_euler": [
                15,
                5,
                9,
                11,
                2,
                14,
                2,
                11,
                7,
                11,
                9,
                15
              ],
              "truck_unused_arcs_after_walk": [],
              "truck_walk_model_order": [
                15,
                5,
                9,
                11,
                2,
                14,
                2,
                11,
                7,
                11,
                9,
                15
              ],
              "truck_unused_arcs_after_model_order": [],
              "truck_walk_eval_preferred": [
                15,
                5,
                9,
                11,
                2,
                14,
                2,
                11,
                7,
                11,
                9,
                15
              ],
              "truck_first_departure_arcs_w": [
                [
                  2,
                  14
                ],
                [
                  5,
                  9
                ],
                [
                  7,
                  11
                ],
                [
                  9,
                  11
                ],
                [
                  11,
                  2
                ],
                [
                  14,
                  2
                ]
              ],
              "truck_last_departure_arcs_a": [
                [
                  2,
                  11
                ],
                [
                  5,
                  9
                ],
                [
                  7,
                  11
                ],
                [
                  9,
                  15
                ],
                [
                  11,
                  9
                ],
                [
                  14,
                  2
                ]
              ],
              "truck_successor_links_b": [
                [
                  14,
                  2,
                  11
                ],
                [
                  11,
                  9,
                  15
                ],
                [
                  2,
                  11,
                  7
                ],
                [
                  7,
                  11,
                  9
                ]
              ],
              "drone_sequence_spt": [
                4,
                1,
                13
              ],
              "drone_arrival_time": {
                "4": 4.0,
                "1": 14.5,
                "13": 31.0
              }
            },
            {
              "depot_internal": 18,
              "truck_assigned_demands": [
                0,
                3,
                8,
                10
              ],
              "drone_assigned_demands": [
                6,
                12
              ],
              "truck_active_arcs": [
                [
                  0,
                  8
                ],
                [
                  0,
                  10
                ],
                [
                  3,
                  10
                ],
                [
                  8,
                  0
                ],
                [
                  8,
                  18
                ],
                [
                  10,
                  0
                ],
                [
                  10,
                  3
                ],
                [
                  18,
                  8
                ]
              ],
              "truck_walk": [
                18,
                8,
                0,
                10,
                3,
                10,
                0,
                8,
                18
              ],
              "truck_walk_euler": [
                18,
                8,
                0,
                10,
                3,
                10,
                0,
                8,
                18
              ],
              "truck_unused_arcs_after_walk": [],
              "truck_walk_model_order": [
                18,
                8,
                0,
                10,
                3,
                10,
                0,
                8,
                18
              ],
              "truck_unused_arcs_after_model_order": [],
              "truck_walk_eval_preferred": [
                18,
                8,
                0,
                10,
                3,
                10,
                0,
                8,
                18
              ],
              "truck_first_departure_arcs_w": [
                [
                  0,
                  10
                ],
                [
                  3,
                  10
                ],
                [
                  8,
                  0
                ],
                [
                  10,
                  3
                ]
              ],
              "truck_last_departure_arcs_a": [
                [
                  0,
                  8
                ],
                [
                  3,
                  10
                ],
                [
                  8,
                  18
                ],
                [
                  10,
                  0
                ]
              ],
              "truck_successor_links_b": [
                [
                  10,
                  0,
                  8
                ],
                [
                  0,
                  8,
                  18
                ],
                [
                  3,
                  10,
                  0
                ]
              ],
              "drone_sequence_spt": [
                12,
                6
              ],
              "drone_arrival_time": {
                "12": 5.5,
                "6": 24.5
              }
            }
          ]
        }
      ]
    },
    "debug_variable_dump": {
      "f_positive": [
        [
          0,
          0,
          8,
          1.0
        ],
        [
          0,
          0,
          10,
          3.0
        ],
        [
          0,
          2,
          11,
          2.0
        ],
        [
          0,
          2,
          14,
          3.0
        ],
        [
          0,
          3,
          10,
          1.0
        ],
        [
          0,
          5,
          9,
          6.0
        ],
        [
          0,
          7,
          11,
          1.0
        ],
        [
          0,
          8,
          0,
          4.0
        ],
        [
          0,
          9,
          11,
          5.0
        ],
        [
          0,
          10,
          0,
          1.0
        ],
        [
          0,
          10,
          3,
          2.0
        ],
        [
          0,
          11,
          2,
          4.0
        ],
        [
          0,
          11,
          7,
          2.0
        ],
        [
          0,
          11,
          9,
          1.0
        ],
        [
          0,
          14,
          2,
          2.0
        ],
        [
          0,
          15,
          5,
          7.0
        ],
        [
          0,
          18,
          8,
          5.0
        ],
        [
          0,
          8,
          -1,
          1.0
        ],
        [
          0,
          9,
          -1,
          1.0
        ]
      ],
      "p_all": [
        [
          0,
          0,
          0.0
        ],
        [
          0,
          1,
          14.5
        ],
        [
          0,
          2,
          0.0
        ],
        [
          0,
          3,
          0.0
        ],
        [
          0,
          4,
          4.0
        ],
        [
          0,
          5,
          0.0
        ],
        [
          0,
          6,
          24.5
        ],
        [
          0,
          7,
          0.0
        ],
        [
          0,
          8,
          0.0
        ],
        [
          0,
          9,
          0.0
        ],
        [
          0,
          10,
          0.0
        ],
        [
          0,
          11,
          0.0
        ],
        [
          0,
          12,
          5.5
        ],
        [
          0,
          13,
          31.0
        ],
        [
          0,
          14,
          0.0
        ]
      ],
      "phi_all": [
        [
          0,
          0,
          4.0
        ],
        [
          0,
          1,
          0.0
        ],
        [
          0,
          2,
          4.0
        ],
        [
          0,
          3,
          2.0
        ],
        [
          0,
          4,
          0.0
        ],
        [
          0,
          5,
          7.0
        ],
        [
          0,
          6,
          0.0
        ],
        [
          0,
          7,
          2.0
        ],
        [
          0,
          8,
          5.0
        ],
        [
          0,
          9,
          6.0
        ],
        [
          0,
          10,
          3.0
        ],
        [
          0,
          11,
          5.0
        ],
        [
          0,
          12,
          0.0
        ],
        [
          0,
          13,
          0.0
        ],
        [
          0,
          14,
          3.0
        ]
      ],
      "psi_all": [
        [
          0,
          0,
          1.0
        ],
        [
          0,
          1,
          16.0
        ],
        [
          0,
          2,
          2.0
        ],
        [
          0,
          3,
          1.0
        ],
        [
          0,
          4,
          16.0
        ],
        [
          0,
          5,
          6.0
        ],
        [
          0,
          6,
          16.0
        ],
        [
          0,
          7,
          2.0
        ],
        [
          0,
          8,
          1.0
        ],
        [
          0,
          9,
          1.0
        ],
        [
          0,
          10,
          1.0
        ],
        [
          0,
          11,
          1.0
        ],
        [
          0,
          12,
          16.0
        ],
        [
          0,
          13,
          16.0
        ],
        [
          0,
          14,
          3.0
        ]
      ],
      "sigma_all": [
        [
          0,
          0,
          1.0
        ],
        [
          0,
          1,
          0.0
        ],
        [
          0,
          2,
          2.0
        ],
        [
          0,
          3,
          1.0
        ],
        [
          0,
          4,
          0.0
        ],
        [
          0,
          5,
          6.0
        ],
        [
          0,
          6,
          0.0
        ],
        [
          0,
          7,
          1.0
        ],
        [
          0,
          8,
          1.0
        ],
        [
          0,
          9,
          1.0
        ],
        [
          0,
          10,
          1.0
        ],
        [
          0,
          11,
          1.0
        ],
        [
          0,
          12,
          0.0
        ],
        [
          0,
          13,
          0.0
        ],
        [
          0,
          14,
          2.0
        ]
      ],
      "u_positive": [
        [
          0,
          15,
          2,
          2.0
        ],
        [
          0,
          15,
          5,
          1.0
        ],
        [
          0,
          15,
          7,
          1.0
        ],
        [
          0,
          15,
          9,
          2.0
        ],
        [
          0,
          15,
          11,
          3.0
        ],
        [
          0,
          15,
          14,
          1.0
        ],
        [
          0,
          18,
          0,
          2.0
        ],
        [
          0,
          18,
          3,
          1.0
        ],
        [
          0,
          18,
          8,
          2.0
        ],
        [
          0,
          18,
          10,
          2.0
        ]
      ],
      "h_positive": [
        [
          0,
          15,
          2,
          1.0
        ],
        [
          0,
          15,
          9,
          1.0
        ],
        [
          0,
          15,
          11,
          2.0
        ],
        [
          0,
          18,
          0,
          1.0
        ],
        [
          0,
          18,
          8,
          1.0
        ],
        [
          0,
          18,
          10,
          1.0
        ]
      ],
      "c_positive": [
        [
          0,
          15,
          2,
          1.0
        ],
        [
          0,
          15,
          5,
          1.0
        ],
        [
          0,
          15,
          7,
          1.0
        ],
        [
          0,
          15,
          9,
          1.0
        ],
        [
          0,
          15,
          11,
          1.0
        ],
        [
          0,
          15,
          14,
          1.0
        ],
        [
          0,
          18,
          0,
          1.0
        ],
        [
          0,
          18,
          3,
          1.0
        ],
        [
          0,
          18,
          8,
          1.0
        ],
        [
          0,
          18,
          10,
          1.0
        ]
      ],
      "z_positive": [
        [
          0,
          15,
          1,
          1.0
        ],
        [
          0,
          15,
          4,
          1.0
        ],
        [
          0,
          15,
          13,
          1.0
        ],
        [
          0,
          18,
          6,
          1.0
        ],
        [
          0,
          18,
          12,
          1.0
        ]
      ],
      "y_positive": [
        [
          0,
          15,
          2,
          11,
          1.0
        ],
        [
          0,
          15,
          2,
          14,
          1.0
        ],
        [
          0,
          15,
          5,
          9,
          1.0
        ],
        [
          0,
          15,
          7,
          11,
          1.0
        ],
        [
          0,
          15,
          9,
          11,
          1.0
        ],
        [
          0,
          15,
          9,
          15,
          1.0
        ],
        [
          0,
          15,
          11,
          2,
          1.0
        ],
        [
          0,
          15,
          11,
          7,
          1.0
        ],
        [
          0,
          15,
          11,
          9,
          1.0
        ],
        [
          0,
          15,
          14,
          2,
          1.0
        ],
        [
          0,
          15,
          15,
          5,
          1.0
        ],
        [
          0,
          18,
          0,
          8,
          1.0
        ],
        [
          0,
          18,
          0,
          10,
          1.0
        ],
        [
          0,
          18,
          3,
          10,
          1.0
        ],
        [
          0,
          18,
          8,
          0,
          1.0
        ],
        [
          0,
          18,
          8,
          18,
          1.0
        ],
        [
          0,
          18,
          10,
          0,
          1.0
        ],
        [
          0,
          18,
          10,
          3,
          1.0
        ],
        [
          0,
          18,
          18,
          8,
          1.0
        ]
      ],
      "w_positive": [
        [
          0,
          15,
          2,
          14,
          1.0
        ],
        [
          0,
          15,
          5,
          9,
          1.0
        ],
        [
          0,
          15,
          7,
          11,
          1.0
        ],
        [
          0,
          15,
          9,
          11,
          1.0
        ],
        [
          0,
          15,
          11,
          2,
          1.0
        ],
        [
          0,
          15,
          14,
          2,
          1.0
        ],
        [
          0,
          18,
          0,
          10,
          1.0
        ],
        [
          0,
          18,
          3,
          10,
          1.0
        ],
        [
          0,
          18,
          8,
          0,
          1.0
        ],
        [
          0,
          18,
          10,
          3,
          1.0
        ]
      ],
      "a_positive": [
        [
          0,
          15,
          2,
          11,
          1.0
        ],
        [
          0,
          15,
          5,
          9,
          1.0
        ],
        [
          0,
          15,
          7,
          11,
          1.0
        ],
        [
          0,
          15,
          9,
          15,
          1.0
        ],
        [
          0,
          15,
          11,
          9,
          1.0
        ],
        [
          0,
          15,
          14,
          2,
          1.0
        ],
        [
          0,
          18,
          0,
          8,
          1.0
        ],
        [
          0,
          18,
          3,
          10,
          1.0
        ],
        [
          0,
          18,
          8,
          18,
          1.0
        ],
        [
          0,
          18,
          10,
          0,
          1.0
        ]
      ],
      "b_positive": [
        [
          0,
          10,
          0,
          8,
          1.0
        ],
        [
          0,
          14,
          2,
          11,
          1.0
        ],
        [
          0,
          0,
          8,
          18,
          1.0
        ],
        [
          0,
          11,
          9,
          15,
          1.0
        ],
        [
          0,
          3,
          10,
          0,
          1.0
        ],
        [
          0,
          2,
          11,
          7,
          1.0
        ],
        [
          0,
          7,
          11,
          9,
          1.0
        ]
      ]
    }
  },
  "solver_reconstructed_from_relaxed_fixing": {
    "tt": {
      "15": [
        15,
        5,
        9,
        11,
        2,
        14,
        2,
        11,
        7,
        11,
        9,
        15
      ],
      "18": [
        18,
        8,
        0,
        10,
        3,
        10,
        0,
        8,
        18
      ]
    },
    "ds": {
      "15": [
        4,
        1,
        13
      ],
      "18": [
        12,
        6
      ]
    },
    "arrival_sim_objective": 11.033333333333333,
    "truck_walk_exact_match_vs_input": {
      "15": false,
      "18": false
    },
    "drone_seq_exact_match_vs_input": {
      "15": true,
      "18": true
    }
  },
  "solver_reconstructed_from_order_fixing": {
    "tt": {
      "15": [
        15,
        5,
        9,
        11,
        2,
        14,
        2,
        11,
        7,
        11,
        9,
        15
      ],
      "18": [
        18,
        8,
        0,
        10,
        3,
        10,
        0,
        8,
        18
      ]
    },
    "ds": {
      "15": [
        4,
        1,
        13
      ],
      "18": [
        12,
        6
      ]
    },
    "arrival_sim_objective": 11.033333333333333,
    "truck_walk_exact_match_vs_model_normalized_input": {
      "15": true,
      "18": true
    },
    "drone_seq_exact_match_vs_input": {
      "15": true,
      "18": true
    }
  },
  "ordered_flow_accounting": {
    "expected_from_explicit_walk": {
      "f_expected_on_arcs": [
        [
          0,
          0,
          8,
          1.0
        ],
        [
          0,
          0,
          10,
          3.0
        ],
        [
          0,
          2,
          11,
          2.0
        ],
        [
          0,
          2,
          14,
          3.0
        ],
        [
          0,
          3,
          10,
          1.0
        ],
        [
          0,
          5,
          9,
          6.0
        ],
        [
          0,
          7,
          11,
          1.0
        ],
        [
          0,
          8,
          0,
          4.0
        ],
        [
          0,
          8,
          18,
          1.0
        ],
        [
          0,
          9,
          11,
          5.0
        ],
        [
          0,
          9,
          15,
          1.0
        ],
        [
          0,
          10,
          0,
          1.0
        ],
        [
          0,
          10,
          3,
          2.0
        ],
        [
          0,
          11,
          2,
          4.0
        ],
        [
          0,
          11,
          7,
          2.0
        ],
        [
          0,
          11,
          9,
          1.0
        ],
        [
          0,
          14,
          2,
          2.0
        ],
        [
          0,
          15,
          5,
          7.0
        ],
        [
          0,
          18,
          8,
          5.0
        ]
      ],
      "sink_expected": [
        [
          0,
          8,
          1.0
        ],
        [
          0,
          9,
          1.0
        ]
      ],
      "per_depot": [
        {
          "depot_internal": 15,
          "closed_tour_used_for_model": [
            15,
            5,
            9,
            11,
            2,
            14,
            2,
            11,
            7,
            11,
            9,
            15
          ],
          "truck_demands_fixed_in_c": [
            2,
            5,
            7,
            9,
            11,
            14
          ],
          "expected_arc_flows": [
            {
              "arc": [
                15,
                5
              ],
              "expected_flow": 7.0
            },
            {
              "arc": [
                5,
                9
              ],
              "expected_flow": 6.0
            },
            {
              "arc": [
                9,
                11
              ],
              "expected_flow": 5.0
            },
            {
              "arc": [
                11,
                2
              ],
              "expected_flow": 4.0
            },
            {
              "arc": [
                2,
                14
              ],
              "expected_flow": 3.0
            },
            {
              "arc": [
                14,
                2
              ],
              "expected_flow": 2.0
            },
            {
              "arc": [
                2,
                11
              ],
              "expected_flow": 2.0
            },
            {
              "arc": [
                11,
                7
              ],
              "expected_flow": 2.0
            },
            {
              "arc": [
                7,
                11
              ],
              "expected_flow": 1.0
            },
            {
              "arc": [
                11,
                9
              ],
              "expected_flow": 1.0
            },
            {
              "arc": [
                9,
                15
              ],
              "expected_flow": 1.0
            }
          ],
          "expected_sink_from_node": 9
        },
        {
          "depot_internal": 18,
          "closed_tour_used_for_model": [
            18,
            8,
            0,
            10,
            3,
            10,
            0,
            8,
            18
          ],
          "truck_demands_fixed_in_c": [
            0,
            3,
            8,
            10
          ],
          "expected_arc_flows": [
            {
              "arc": [
                18,
                8
              ],
              "expected_flow": 5.0
            },
            {
              "arc": [
                8,
                0
              ],
              "expected_flow": 4.0
            },
            {
              "arc": [
                0,
                10
              ],
              "expected_flow": 3.0
            },
            {
              "arc": [
                10,
                3
              ],
              "expected_flow": 2.0
            },
            {
              "arc": [
                3,
                10
              ],
              "expected_flow": 1.0
            },
            {
              "arc": [
                10,
                0
              ],
              "expected_flow": 1.0
            },
            {
              "arc": [
                0,
                8
              ],
              "expected_flow": 1.0
            },
            {
              "arc": [
                8,
                18
              ],
              "expected_flow": 1.0
            }
          ],
          "expected_sink_from_node": 8
        }
      ]
    },
    "comparison_to_model_f": {
      "available": true,
      "arc_flow_rows": [
        [
          0,
          0,
          8,
          1.0,
          1.0,
          0.0
        ],
        [
          0,
          0,
          10,
          3.0,
          3.0,
          0.0
        ],
        [
          0,
          2,
          11,
          2.0,
          2.0,
          0.0
        ],
        [
          0,
          2,
          14,
          3.0,
          3.0,
          0.0
        ],
        [
          0,
          3,
          10,
          1.0,
          1.0,
          0.0
        ],
        [
          0,
          5,
          9,
          6.0,
          6.0,
          0.0
        ],
        [
          0,
          7,
          11,
          1.0,
          1.0,
          0.0
        ],
        [
          0,
          8,
          -1,
          null,
          1.0,
          null
        ],
        [
          0,
          8,
          0,
          4.0,
          4.0,
          0.0
        ],
        [
          0,
          8,
          18,
          1.0,
          null,
          null
        ],
        [
          0,
          9,
          -1,
          null,
          1.0,
          null
        ],
        [
          0,
          9,
          11,
          5.0,
          5.0,
          0.0
        ],
        [
          0,
          9,
          15,
          1.0,
          null,
          null
        ],
        [
          0,
          10,
          0,
          1.0,
          1.0,
          0.0
        ],
        [
          0,
          10,
          3,
          2.0,
          2.0,
          0.0
        ],
        [
          0,
          11,
          2,
          4.0,
          4.0,
          0.0
        ],
        [
          0,
          11,
          7,
          2.0,
          2.0,
          0.0
        ],
        [
          0,
          11,
          9,
          1.0,
          1.0,
          0.0
        ],
        [
          0,
          14,
          2,
          2.0,
          2.0,
          0.0
        ],
        [
          0,
          15,
          5,
          7.0,
          7.0,
          0.0
        ],
        [
          0,
          18,
          8,
          5.0,
          5.0,
          0.0
        ]
      ],
      "arc_flow_mismatches": [
        [
          0,
          8,
          -1,
          null,
          1.0,
          null
        ],
        [
          0,
          8,
          18,
          1.0,
          null,
          null
        ],
        [
          0,
          9,
          -1,
          null,
          1.0,
          null
        ],
        [
          0,
          9,
          15,
          1.0,
          null,
          null
        ]
      ],
      "sink_rows": [
        [
          0,
          8,
          1.0,
          1.0,
          0.0
        ],
        [
          0,
          9,
          1.0,
          1.0,
          0.0
        ]
      ]
    }
  },
  "gap": {
    "raw_arrival_minus_relaxed_paper": 0.0,
    "raw_arrival_minus_ordered_paper": 0.0,
    "normalized_arrival_minus_ordered_paper": 0.0,
    "relaxed_reconstructed_arrival_minus_raw_arrival": 0.0,
    "ordered_reconstructed_arrival_minus_normalized_arrival": 0.0,
    "ordered_reconstructed_arrival_minus_ordered_paper": 0.0
  },
  "notes": [
    "arrival_sim uses the explicit TTk/DSk directly on one scenario.",
    "arrival_sim_on_model_normalized_walk uses the deduplicated and depot-closed walk that is actually encoded into the fixed-order MIP.",
    "paper_exact_fixed_primary_binaries_only fixes only y/c/z and leaves order hints free.",
    "paper_exact_fixed_primary_and_order_binaries also fixes w/a/b derived from the explicit walk.",
    "If the explicit truck walk repeats directed arcs, binary y collapses multiplicity and the two evaluations are not strictly the same object.",
    "If the explicit truck walk does not end at its depot, the debug pipeline auto-closes it before building y."
  ]
}