{
  "report_path": "outputs/instance3_full_a1_v2.json",
  "mode": "full-a1",
  "checks": [
    {
      "name": "summary.best_expected_obj consistent with runs",
      "ok": true,
      "detail": "calc=11.3000000000, report=11.3000000000"
    },
    {
      "name": "summary.avg_expected_obj consistent with runs",
      "ok": true,
      "detail": "calc=11.5933333333, report=11.5933333333"
    },
    {
      "name": "summary.std_expected_obj consistent with runs",
      "ok": true,
      "detail": "calc=0.2151485275, report=0.2151485275"
    },
    {
      "name": "summary.best_seed consistent with runs",
      "ok": true,
      "detail": "calc=2, report=2"
    },
    {
      "name": "summary.best_x_open consistent with runs",
      "ok": true,
      "detail": "calc=[15, 18], report=[15, 18]"
    },
    {
      "name": "all runtime_sec are non-negative",
      "ok": true,
      "detail": "runtime check"
    },
    {
      "name": "best_seed expected objective consistent with scenario details",
      "ok": true,
      "detail": "calc=11.3000000000, report=11.3000000000"
    },
    {
      "name": "recomputed best seed expected objective matches report",
      "ok": true,
      "detail": "recomputed=11.3000000000, report=11.3000000000"
    }
  ],
  "summary": {
    "run_count": 3,
    "scenario_count": 10,
    "valid_count": 10,
    "improved_count": 10,
    "valid_rate": 1.0,
    "improved_rate": 1.0
  },
  "recompute_summary": {
    "scenario_count": 10,
    "valid_count": 10,
    "improved_count": 10,
    "valid_rate": 1.0,
    "improved_rate": 1.0,
    "recomputed_expected_obj": 11.3
  },
  "passed_checks": 8,
  "failed_checks": 0
}